discordup/__init__.py
discordup/__main__.py
discordup/_discord.py
discordup/_distro.py
discordup/cli.py
discordup/discord.py
discordup-0.0.11.dist-info/LICENSE
discordup-0.0.11.dist-info/METADATA
discordup-0.0.11.dist-info/WHEEL
discordup-0.0.11.dist-info/entry_points.txt
discordup-0.0.11.dist-info/top_level.txt
discordup-0.0.11.dist-info/RECORD
