Metadata-Version: 2.1
Name: discordup
Version: 0.0.11
Summary: Update and install Discord via the terminal on linux
Home-page: https://github.com/jona799t/discordup
Author: jona799t
License: GsetPL-3.0
Platform: UNKNOWN
Requires-Python: >3.0
License-File: LICENSE
Requires-Dist: requests
